Workbook
Name EstimateInputFilingStatusCell: Estimator!$G$8
Name EstimateInputTaxYearCell: Estimator!$C$8
Name InRangeLabelCell: Parameters!$G$6
Name MaxIncomeCell: Parameters!$G$10
Name NotFoundLabelCell: Parameters!$G$8
Name OutOfRangeLabelCell: Parameters!$G$7
Name SelectionValidLabelCell: Parameters!$G$9

Sheet ReadMe
B3: Purpose
B4: This spreadsheet helps you quickly estimate your total federal tax liability by combining the most common tax types for employed individuals in one place. Key benefit of this calculator: Most tax estimators focus on only one tax type (e.g., income tax). This tool calculates and properly combines most common tax types: - Federal Income Tax (including Alternative Minimum Tax (AMT)) - Long-Term Capital Gains Tax - Social Security Tax - Medicare Taxes (including Additional Medicare Tax and NIIT) Philosophy: This is an estimation tool, not a precise calculator. It intentionally omits some deductions to keep things simple. It's better to slightly overestimate (and get a refund) than underestimate (and face penalties).
B6: How to use
B7: 1. If you are viewing the public read-only version, get your own private copy of the calculator: - Go to: File > Create a Copy. To use with Excel for Desktop (Windows or Mac), select 'Download a Copy'. To use with Excel Online (free), select 'Create a copy online'. - Alternatively, download the calculator Excel file directly from the GitHub repo (link below). 2. Input Your Income ('Estomator' tab, orange cells only): - Enter your estimated income in section 'Your extimated income'. - Each income category has 3 input fields. Use them however you like (they're simply added together). - Only edit orange cells. All other cells are auto-computed. - Some input cells are pre-filled with sample values. Make sure to override with your values. 3. Review Your Results: - 'Total Tax Summary' section: View estimated tax by type and your total. - Detail sections below: See exactly how each tax is calculated. - 'Parameters' tab: Reference tax rates and brackets for each year.
B8: Link to this calculator on GitHub:
B9: https://github.com/macrogreg/Combined-Income-Tax-Estimator
B11: Tax types not considered
B12: - State and local taxes. - Some nuances of Alternative Minimum Tax (AMT), such as Incentive Stock Options (ISO) exercise tax. This can significantly impact the AMT. There may be other AMT nuances that are not considered. - Self-Employment Tax. - There may be others, so focus on what is explicitly covered (see above).
B15: ⚠️ This calculator is not a qualified tax advice.
B16: This tool is for estimation purposes only. It should be reasonably accurate for ~90% of employed individuals. The calculator accounts for common income types, such as W-2, capital gains, rental income, and others. For fully reliable tax calculations, expecially for complex tax situations, always consult a qualified tax professional!

Sheet Estimator
B2: * All calculated values are estimates. | F2: Select/enter values for orange fields.
B3: The author is not a qualified tax expert. | F3: Do not modify other fields (auto-computed).
B5: Your extimated income
B6: Enter your income in this section. Tax estimates will be based on it.
B8: Tax Year: | C8: 2025 | F8: Filing Status: | G8: Single
B10: Earned Income | F10: Deductions towards Adjusted Gross Income (AGI) | J10: Regular Income Tax Deductions
B11: e.g., wages, tips, bonuses, benefits, shares, … | F11: e.g., certain 401k, IRA & HSA contributions, certain education expenses, certain other expenses | J11: below-the-line items: use standard OR itemize, e.g., mortgage interest, charity, state & local taxes, …
B13: Gross Wages A: | C13: 80000 | F13: AGI above-the-line Deductions A: | G13: 5000 | J13: The larger option will be used:
B14: Gross Wages B: | C14: 0 | F14: AGI above-the-line Deductions B: | G14: 0 | J14: Standard Deduction for selected status: | K14: =_xlfn.XLOOKUP(TRUE, StandardDeductionAmountTable[IsSelected], StandardDeductionAmountTable[Standard Deduction Amount], NotFoundLabelCell) -> 15000
B15: Gross Wages C: | C15: 0 | F15: AGI above-the-line Deductions C: | G15: 0 | J15: Itemized Deductions total: | K15: 0 | L15: (leave $0, if not itemizing)
B16: Total Gross Wages: | C16: =SUM(C13:C15) -> 80000 | D16: =IF( AND(0 <= C16, C16 <= MaxIncomeCell), InRangeLabelCell, OutOfRangeLabelCell ) -> ✔ | F16: Total AGI above-the-line Deductions: | G16: =SUM(G13:G15) -> 5000 | H16: =IF( AND(0 <= G16, G16 <= MaxIncomeCell), InRangeLabelCell, OutOfRangeLabelCell ) -> ✔ | J16: Deduction Amount: | K16: =MAX(K14:K15) -> 15000
B19: Passive Income & Similar | F19: Long-term Capital Gains | J19: Short-term Capital Gains
B20: e.g., rental income, interest, non-qualified dividends, … | F20: e.g., qualidied dividends, realized income from sold assets | J20: e.g., realized income from sold short-term assets
B22: Net Rental & similar Income A: | C22: 10000 | F22: Long-term Capital Gains A: | G22: 5000 | J22: Short-term Capital Gains A: | K22: 2000
B23: Net Rental & similar Income B: | C23: 0 | F23: Long-term Capital Gains B: | G23: 0 | J23: Short-term Capital Gains B: | K23: 0
B24: Net Rental & similar Income C: | C24: 0 | F24: Long-term Capital Gains C: | G24: 0 | J24: Short-term Capital Gains C: | K24: 0
B25: Total Rental & similar Income: | C25: =SUM(C22:C24) -> 10000 | D25: =IF( AND(0 <= C25, C25 <= MaxIncomeCell), InRangeLabelCell, OutOfRangeLabelCell ) -> ✔ | F25: Total Long-term Capital Gains: | G25: =SUM(G22:G24) -> 5000 | H25: =IF( AND(0 <= G25, G25 <= MaxIncomeCell), InRangeLabelCell, OutOfRangeLabelCell ) -> ✔ | J25: Total Short-term Capital Gains: | K25: =SUM(K22:K24) -> 2000 | L25: =IF( AND(0 <= K25, K25 <= MaxIncomeCell), InRangeLabelCell, OutOfRangeLabelCell ) -> ✔
B28: Income Summary
B29: This section summarizes your income entered above.
B31: Gross Income | F31: Adjusted Gross Income (AGI)
B33: =$B$16 -> Total Gross Wages: | C33: =$C$16 -> 80000 | D33: =_xlfn.LET( _xlpm.FormulaText, _xlfn.FORMULATEXT(C33), HYPERLINK( "#" & SUBSTITUTE(_xlpm.FormulaText, "=", ""), _xlpm.FormulaText ) ) -> = $C$16 | F33: =$B$16 -> Total Gross Wages: | G33: =$C$16 -> 80000 | H33: =_xlfn.LET( _xlpm.FormulaText, _xlfn.FORMULATEXT(G33), HYPERLINK( "#" & SUBSTITUTE(_xlpm.FormulaText, "=", ""), _xlpm.FormulaText ) ) -> = $C$16
B34: =$B$25 -> Total Rental & similar Income: | C34: =$C$25 -> 10000 | D34: =_xlfn.LET( _xlpm.FormulaText, _xlfn.FORMULATEXT(C34), HYPERLINK( "#" & SUBSTITUTE(_xlpm.FormulaText, "=", ""), _xlpm.FormulaText ) ) -> = $C$25 | F34: =$B$25 -> Total Rental & similar Income: | G34: =$C$25 -> 10000 | H34: =_xlfn.LET( _xlpm.FormulaText, _xlfn.FORMULATEXT(G34), HYPERLINK( "#" & SUBSTITUTE(_xlpm.FormulaText, "=", ""), _xlpm.FormulaText ) ) -> = $C$25
B35: =$F$25 -> Total Long-term Capital Gains: | C35: =$G$25 -> 5000 | D35: =_xlfn.LET( _xlpm.FormulaText, _xlfn.FORMULATEXT(C35), HYPERLINK( "#" & SUBSTITUTE(_xlpm.FormulaText, "=", ""), _xlpm.FormulaText ) ) -> = $G$25 | F35: =$F$25 -> Total Long-term Capital Gains: | G35: =$G$25 -> 5000 | H35: =_xlfn.LET( _xlpm.FormulaText, _xlfn.FORMULATEXT(G35), HYPERLINK( "#" & SUBSTITUTE(_xlpm.FormulaText, "=", ""), _xlpm.FormulaText ) ) -> = $G$25
B36: =$J$25 -> Total Short-term Capital Gains: | C36: =$K$25 -> 2000 | D36: =_xlfn.LET( _xlpm.FormulaText, _xlfn.FORMULATEXT(C36), HYPERLINK( "#" & SUBSTITUTE(_xlpm.FormulaText, "=", ""), _xlpm.FormulaText ) ) -> = $K$25 | F36: =$J$25 -> Total Short-term Capital Gains: | G36: =$K$25 -> 2000 | H36: =_xlfn.LET( _xlpm.FormulaText, _xlfn.FORMULATEXT(G36), HYPERLINK( "#" & SUBSTITUTE(_xlpm.FormulaText, "=", ""), _xlpm.FormulaText ) ) -> = $K$25
B37: Total Gross Income: | C37: =SUM(C33:C36) -> 97000 | D37: =IF( AND(0 <= C37, C37 <= MaxIncomeCell), InRangeLabelCell, OutOfRangeLabelCell ) -> ✔ | F37: =$F$16 -> Total AGI above-the-line Deductions: | G37: =- $G$16 -> -5000 | H37: =_xlfn.LET( _xlpm.FormulaText, _xlfn.FORMULATEXT(G37), HYPERLINK( "#" & SUBSTITUTE(SUBSTITUTE(_xlpm.FormulaText, "-", ""), "=", ""), _xlpm.FormulaText ) ) -> = - $G$16
F38: Total AGI (Adjusted Gross Income): | G38: =SUM(G33:G37) -> 92000 | H38: =IF( AND(0 <= G38, G38 <= MaxIncomeCell), InRangeLabelCell, OutOfRangeLabelCell ) -> ✔
B40: Total Tax Summary
B41: This is the result section. It summarizes your estimated taxes.
B43: Total Tax Estimate | F43: Total Net Income Estimate
B45: Tax Type | C45: Amount | F45: =$B$37 -> Total Gross Income: | G45: =$C$37 -> 97000 | H45: =_xlfn.LET( _xlpm.FormulaText, _xlfn.FORMULATEXT(G45), HYPERLINK( "#" & SUBSTITUTE(_xlpm.FormulaText, "=", ""), _xlpm.FormulaText ) ) -> = $C$37
B46: =$J$73 -> Effective Federal Income Tax | C46: =$K$78 -> 10754 | D46: =_xlfn.LET( _xlpm.FormulaText, _xlfn.FORMULATEXT(C46), HYPERLINK( "#" & SUBSTITUTE(_xlpm.FormulaText, "=", ""), _xlpm.FormulaText ) ) -> = $K$78 | F46: =TotalTaxEstimateTable[[#Totals],[Tax Type]] -> Total Tax Estimate: | G46: =TotalTaxEstimateTable[[#Totals],[Amount]] -> 17624
B47: =B103 -> Long Term Capital Gain Tax (LTCG) | C47: =$C$121 -> 750 | D47: =_xlfn.LET( _xlpm.FormulaText, _xlfn.FORMULATEXT(C47), HYPERLINK( "#" & SUBSTITUTE(_xlpm.FormulaText, "=", ""), _xlpm.FormulaText ) ) -> = $C$121 | F47: Total tax as percentage of Income: | G47: =G46 / G45 -> 0.18169072 | H47: =_xlfn.LET( _xlpm.FormulaText, _xlfn.FORMULATEXT(G47), _xlpm.FormulaText ) -> = G46 / G45
B48: =$J$57 -> Social Security Tax | C48: =$K$64 -> 4960 | D48: =_xlfn.LET( _xlpm.FormulaText, _xlfn.FORMULATEXT(C48), HYPERLINK( "#" & SUBSTITUTE(_xlpm.FormulaText, "=", ""), _xlpm.FormulaText ) ) -> = $K$64 | F48: Net Income Estimate | G48: =G45 - G46 -> 79376 | H48: =_xlfn.LET( _xlpm.FormulaText, _xlfn.FORMULATEXT(G48), _xlpm.FormulaText ) -> = G45 - G46
B49: =$B$57 -> Medicare Wages Tax | C49: =$C$67 -> 1160 | D49: =_xlfn.LET( _xlpm.FormulaText, _xlfn.FORMULATEXT(C49), HYPERLINK( "#" & SUBSTITUTE(_xlpm.FormulaText, "=", ""), _xlpm.FormulaText ) ) -> = $C$67
B50: =$F$57 -> Medicare Net Investment Income Tax (NIIT) | C50: =$G$68 -> 0 | D50: =_xlfn.LET( _xlpm.FormulaText, _xlfn.FORMULATEXT(C50), HYPERLINK( "#" & SUBSTITUTE(_xlpm.FormulaText, "=", ""), _xlpm.FormulaText ) ) -> = $G$68
B51: Total Tax Estimate: | C51: =SUBTOTAL(109,TotalTaxEstimateTable[Amount]) -> 17624
B55: Federal Insurance Contributions & Affordable Care Act Taxes
B57: Medicare Wages Tax | F57: Medicare Net Investment Income Tax (NIIT) | J57: Social Security Tax
B59: Taxable Medicare Wages Amount: | C59: =$C$16 -> 80000 | D59: =_xlfn.LET( _xlpm.FormulaText, _xlfn.FORMULATEXT(C59), HYPERLINK( "#" & SUBSTITUTE(_xlpm.FormulaText, "=", ""), _xlpm.FormulaText ) ) -> = $C$16 | F59: Net Investment Amount: | G59: =$C$25 + $G$25 + $K$25 -> 17000 | H59: =IF( AND(0 <= G59, G59 <= MaxIncomeCell), InRangeLabelCell, OutOfRangeLabelCell ) -> ✔ | J59: Max Taxable Amount: | K59: =_xlfn.XLOOKUP(TRUE, SocialSecurityTaxRateTable[IsSelected], SocialSecurityTaxRateTable[Max Taxable Income], NotFoundLabelCell) -> 176100 | L59: {=_xlfn.LET( _xlpm.LookupTableName, "SocialSecurityTaxRateTable", _xlpm.ValueColumnName, "Max Taxable Income", _xlpm.TableValueColumn, INDIRECT(_xlpm.LookupTableName & "[" & _xlpm.ValueColumnName & "]"), _xlpm.TableRowNum, _xlfn.XMATCH(TRUE, INDIRECT(_xlpm.LookupTableName & "[IsSelected]")), _xlpm.LinkTarget, IF(ISNA(_xlpm.TableRowNum), "#" & CELL("address", L59), "#" & CELL("address", INDEX(_xlpm.TableValueColumn, _xlpm.TableRowNum)) ), _xlpm.LinkLabel, IF(ISNA(_xlpm.TableRowNum), NotFoundLabelCell, "in " & _xlpm.LookupTableName ), HYPERLINK(_xlpm.LinkTarget, _xlpm.LinkLabel) )} -> in SocialSecurityTaxRateTable
F60: Applicable Modified Adjusted Gross Income (MAGI): | G60: =$C$37 -> 97000 | H60: =_xlfn.LET( _xlpm.FormulaText, _xlfn.FORMULATEXT(G60), HYPERLINK( "#" & SUBSTITUTE(_xlpm.FormulaText, "=", ""), _xlpm.FormulaText ) ) -> = $C$37
B61: Marginal Rate: | C61: =_xlfn.XLOOKUP(TRUE, MedicareWageTaxRateTable[IsSelected], MedicareWageTaxRateTable[Medicare Rate], NotFoundLabelCell) -> 0.0145 | D61: {=_xlfn.LET( _xlpm.LookupTableName, "MedicareWageTaxRateTable", _xlpm.ValueColumnName, "Medicare Rate", _xlpm.TableValueColumn, INDIRECT(_xlpm.LookupTableName & "[" & _xlpm.ValueColumnName & "]"), _xlpm.TableRowNum, _xlfn.XMATCH(TRUE, INDIRECT(_xlpm.LookupTableName & "[IsSelected]")), _xlpm.LinkTarget, IF(ISNA(_xlpm.TableRowNum), "#" & CELL("address", D61), "#" & CELL("address", INDEX(_xlpm.TableValueColumn, _xlpm.TableRowNum)) ), _xlpm.LinkLabel, IF(ISNA(_xlpm.TableRowNum), NotFoundLabelCell, "in " & _xlpm.LookupTableName ), HYPERLINK(_xlpm.LinkTarget, _xlpm.LinkLabel) )} -> in MedicareWageTaxRateTable | J61: Applicable Rate: | K61: =_xlfn.XLOOKUP(TRUE, SocialSecurityTaxRateTable[IsSelected], SocialSecurityTaxRateTable[SocialSecurity Rate], NotFoundLabelCell) -> 0.062 | L61: {=_xlfn.LET( _xlpm.LookupTableName, "SocialSecurityTaxRateTable", _xlpm.ValueColumnName, "SocialSecurity Rate", _xlpm.TableValueColumn, INDIRECT(_xlpm.LookupTableName & "[" & _xlpm.ValueColumnName & "]"), _xlpm.TableRowNum, _xlfn.XMATCH(TRUE, INDIRECT(_xlpm.LookupTableName & "[IsSelected]")), _xlpm.LinkTarget, IF(ISNA(_xlpm.TableRowNum), "#" & CELL("address", L61), "#" & CELL("address", INDEX(_xlpm.TableValueColumn, _xlpm.TableRowNum)) ), _xlpm.LinkLabel, IF(ISNA(_xlpm.TableRowNum), NotFoundLabelCell, "in " & _xlpm.LookupTableName ), HYPERLINK(_xlpm.LinkTarget, _xlpm.LinkLabel) )} -> in SocialSecurityTaxRateTable
B62: Marginal rate Bracket Start: | C62: =_xlfn.XLOOKUP(TRUE, MedicareWageTaxRateTable[IsSelected], MedicareWageTaxRateTable[RangeStart], NotFoundLabelCell) -> 0 | D62: {=_xlfn.LET( _xlpm.LookupTableName, "MedicareWageTaxRateTable", _xlpm.ValueColumnName, "RangeStart", _xlpm.TableValueColumn, INDIRECT(_xlpm.LookupTableName & "[" & _xlpm.ValueColumnName & "]"), _xlpm.TableRowNum, _xlfn.XMATCH(TRUE, INDIRECT(_xlpm.LookupTableName & "[IsSelected]")), _xlpm.LinkTarget, IF(ISNA(_xlpm.TableRowNum), "#" & CELL("address", D62), "#" & CELL("address", INDEX(_xlpm.TableValueColumn, _xlpm.TableRowNum)) ), _xlpm.LinkLabel, IF(ISNA(_xlpm.TableRowNum), NotFoundLabelCell, "in " & _xlpm.LookupTableName ), HYPERLINK(_xlpm.LinkTarget, _xlpm.LinkLabel) )} -> in MedicareWageTaxRateTable | F62: Applicable MAGI Threshold: | G62: =_xlfn.XLOOKUP(TRUE, MedicareNetInvestIncomeTaxTable[IsSelected], MedicareNetInvestIncomeTaxTable[Modified AGI Threshold], NotFoundLabelCell) -> 200000 | H62: {=_xlfn.LET( _xlpm.LookupTableName, "MedicareNetInvestIncomeTaxTable", _xlpm.ValueColumnName, "Modified AGI Threshold", _xlpm.TableValueColumn, INDIRECT(_xlpm.LookupTableName & "[" & _xlpm.ValueColumnName & "]"), _xlpm.TableRowNum, _xlfn.XMATCH(TRUE, INDIRECT(_xlpm.LookupTableName & "[IsSelected]")), _xlpm.LinkTarget, IF(ISNA(_xlpm.TableRowNum), "#" & CELL("address", H62), "#" & CELL("address", INDEX(_xlpm.TableValueColumn, _xlpm.TableRowNum)) ), _xlpm.LinkLabel, IF(ISNA(_xlpm.TableRowNum), NotFoundLabelCell, "in " & _xlpm.LookupTableName ), HYPERLINK(_xlpm.LinkTarget, _xlpm.LinkLabel) )} -> in MedicareNetInvestIncomeTaxTable | J62: Applicable Taxable Amount: | K62: =MIN( $C$16, K59 ) -> 80000 | L62: =_xlfn.LET( _xlpm.FormulaText, _xlfn.FORMULATEXT(K62), _xlpm.FormulaText ) -> = MIN( $C$16, K59 )
F63: Is NIIT applicable: | G63: =G60 >= G62 -> FALSE | H63: =_xlfn.LET( _xlpm.FormulaText, _xlfn.FORMULATEXT(G63), _xlpm.FormulaText ) -> = G60 >= G62
B64: Subtotal of lower rate brackets: | C64: =IF( C59 = 0, 0, _xlfn.XLOOKUP(TRUE, MedicareWageTaxRateTable[IsSelected], MedicareWageTaxRateTable[SumLowerRanges], NotFoundLabelCell) ) -> 0 | D64: {=_xlfn.LET( _xlpm.LookupTableName, "MedicareWageTaxRateTable", _xlpm.ValueColumnName, "SumLowerRanges", _xlpm.TableValueColumn, INDIRECT(_xlpm.LookupTableName & "[" & _xlpm.ValueColumnName & "]"), _xlpm.TableRowNum, _xlfn.XMATCH(TRUE, INDIRECT(_xlpm.LookupTableName & "[IsSelected]")), _xlpm.LinkTarget, IF(ISNA(_xlpm.TableRowNum), "#" & CELL("address", D64), "#" & CELL("address", INDEX(_xlpm.TableValueColumn, _xlpm.TableRowNum)) ), _xlpm.LinkLabel, IF(ISNA(_xlpm.TableRowNum), NotFoundLabelCell, "in " & _xlpm.LookupTableName ), HYPERLINK(_xlpm.LinkTarget, _xlpm.LinkLabel) )} -> in MedicareWageTaxRateTable | J64: Total Medicare Wages Tax: | K64: =K62 * K61 -> 4960 | L64: =_xlfn.LET( _xlpm.FormulaText, _xlfn.FORMULATEXT(K64), _xlpm.FormulaText ) -> = K62 * K61
B65: Subtotal in marginal rate bracket: | C65: =IF( C59 = 0, 0, (C59 - C62) * C61 ) -> 1160 | F65: Medicare Net Investment Income Tax Rate: | G65: =_xlfn.XLOOKUP(TRUE, MedicareNetInvestIncomeTaxTable[IsSelected], MedicareNetInvestIncomeTaxTable[NetInvestInc Rate], NotFoundLabelCell) -> 0.038 | H65: {=_xlfn.LET( _xlpm.LookupTableName, "MedicareNetInvestIncomeTaxTable", _xlpm.ValueColumnName, "NetInvestInc Rate", _xlpm.TableValueColumn, INDIRECT(_xlpm.LookupTableName & "[" & _xlpm.ValueColumnName & "]"), _xlpm.TableRowNum, _xlfn.XMATCH(TRUE, INDIRECT(_xlpm.LookupTableName & "[IsSelected]")), _xlpm.LinkTarget, IF(ISNA(_xlpm.TableRowNum), "#" & CELL("address", H65), "#" & CELL("address", INDEX(_xlpm.TableValueColumn, _xlpm.TableRowNum)) ), _xlpm.LinkLabel, IF(ISNA(_xlpm.TableRowNum), NotFoundLabelCell, "in " & _xlpm.LookupTableName ), HYPERLINK(_xlpm.LinkTarget, _xlpm.LinkLabel) )} -> in MedicareNetInvestIncomeTaxTable
F66: Taxable Medicare NIIT Amount: | G66: =IF( G63, MIN( G59, MAX(G60-G62, 0)), 0 ) -> 0
B67: Total Medicare Wages Tax: | C67: =C64 + C65 -> 1160 | D67: =_xlfn.LET( _xlpm.FormulaText, _xlfn.FORMULATEXT(C67), _xlpm.FormulaText ) -> = C64 + C65
F68: Total Medicare NIIT: | G68: =IF( G63, G66 * G65, 0 ) -> 0
B71: Federal Income Taxes
B73: Regular Income Tax | F73: Alternative Minimum Tax (AMT) | J73: Effective Federal Income Tax
B75: =$B$16 -> Total Gross Wages: | C75: =$C$16 -> 80000 | D75: =_xlfn.LET( _xlpm.FormulaText, _xlfn.FORMULATEXT(C75), HYPERLINK( "#" & SUBSTITUTE(_xlpm.FormulaText, "=", ""), _xlpm.FormulaText ) ) -> = $C$16 | F75: =$B$16 -> Total Gross Wages: | G75: =$C$16 -> 80000 | H75: =_xlfn.LET( _xlpm.FormulaText, _xlfn.FORMULATEXT(G75), HYPERLINK( "#" & SUBSTITUTE(_xlpm.FormulaText, "=", ""), _xlpm.FormulaText ) ) -> = $C$16 | J75: =B73 -> Regular Income Tax | K75: =C92 -> 10754 | L75: =_xlfn.LET( _xlpm.FormulaText, _xlfn.FORMULATEXT(K75), HYPERLINK( "#" & SUBSTITUTE(_xlpm.FormulaText, "=", ""), _xlpm.FormulaText ) ) -> = C92
B76: =$B$25 -> Total Rental & similar Income: | C76: =$C$25 -> 10000 | D76: =_xlfn.LET( _xlpm.FormulaText, _xlfn.FORMULATEXT(C76), HYPERLINK( "#" & SUBSTITUTE(_xlpm.FormulaText, "=", ""), _xlpm.FormulaText ) ) -> = $C$25 | F76: =$B$25 -> Total Rental & similar Income: | G76: =$C$25 -> 10000 | H76: =_xlfn.LET( _xlpm.FormulaText, _xlfn.FORMULATEXT(G76), HYPERLINK( "#" & SUBSTITUTE(_xlpm.FormulaText, "=", ""), _xlpm.FormulaText ) ) -> = $C$25 | J76: =F73 -> Alternative Minimum Tax (AMT) | K76: =G99 -> 0 | L76: =_xlfn.LET( _xlpm.FormulaText, _xlfn.FORMULATEXT(K76), HYPERLINK( "#" & SUBSTITUTE(_xlpm.FormulaText, "=", ""), _xlpm.FormulaText ) ) -> = G99
B77: =$J$25 -> Total Short-term Capital Gains: | C77: =$K$25 -> 2000 | D77: =_xlfn.LET( _xlpm.FormulaText, _xlfn.FORMULATEXT(C77), HYPERLINK( "#" & SUBSTITUTE(_xlpm.FormulaText, "=", ""), _xlpm.FormulaText ) ) -> = $K$25 | F77: =$J$25 -> Total Short-term Capital Gains: | G77: =$K$25 -> 2000 | H77: =_xlfn.LET( _xlpm.FormulaText, _xlfn.FORMULATEXT(G77), HYPERLINK( "#" & SUBSTITUTE(_xlpm.FormulaText, "=", ""), _xlpm.FormulaText ) ) -> = $K$25
B78: Total Applicable Gross Income: | C78: =SUM(C75:C77) -> 92000 | F78: Total Applicable Gross Income: | G78: =SUM(G75:G77) -> 92000 | J78: =J73 -> Effective Federal Income Tax | K78: =MAX( K75, K76 ) -> 10754 | L78: =_xlfn.LET( _xlpm.FormulaText, _xlfn.FORMULATEXT(K78), _xlpm.FormulaText ) -> = MAX( K75, K76 )
J79: (the larger of the two above alternatives)
B80: =$F$16 -> Total AGI above-the-line Deductions: | C80: =- $G$16 -> -5000 | D80: =_xlfn.LET( _xlpm.FormulaText, _xlfn.FORMULATEXT(C80), HYPERLINK( "#" & SUBSTITUTE(SUBSTITUTE(_xlpm.FormulaText, "-", ""), "=", ""), _xlpm.FormulaText ) ) -> = - $G$16 | F80: =$F$16 -> Total AGI above-the-line Deductions: | G80: =- $G$16 -> -5000 | H80: =_xlfn.LET( _xlpm.FormulaText, _xlfn.FORMULATEXT(G80), HYPERLINK( "#" & SUBSTITUTE(SUBSTITUTE(_xlpm.FormulaText, "-", ""), "=", ""), _xlpm.FormulaText ) ) -> = - $G$16
B81: =$J$10 -> Regular Income Tax Deductions | C81: =- $K$16 -> -15000 | D81: =_xlfn.LET( _xlpm.FormulaText, _xlfn.FORMULATEXT(C81), HYPERLINK( "#" & SUBSTITUTE(SUBSTITUTE(_xlpm.FormulaText, "-", ""), "=", ""), _xlpm.FormulaText ) ) -> = - $K$16 | F81: Total Applicable Deductions: | G81: =SUM(G80:G80) -> -5000
B82: Total Applicable Deductions: | C82: =SUM(C80:C81) -> -20000
F83: Alternative Minimum Taxable Income (AMTI) : | G83: =MAX( G78 + G81, 0 ) -> 87000
B84: Applicable Regular Taxable Amount: | C84: =MAX( C78 + C82, 0 ) -> 72000
F85: Basis AMT Exemption: | G85: =_xlfn.XLOOKUP(TRUE, AlternativeMimumumTaxThresholdsTable[IsSelected], AlternativeMimumumTaxThresholdsTable[AMT Exemption], NotFoundLabelCell) -> 88100 | H85: {=_xlfn.LET( _xlpm.LookupTableName, "AlternativeMimumumTaxThresholdsTable", _xlpm.ValueColumnName, "AMT Exemption", _xlpm.TableValueColumn, INDIRECT(_xlpm.LookupTableName & "[" & _xlpm.ValueColumnName & "]"), _xlpm.TableRowNum, _xlfn.XMATCH(TRUE, INDIRECT(_xlpm.LookupTableName & "[IsSelected]")), _xlpm.LinkTarget, IF(ISNA(_xlpm.TableRowNum), "#" & CELL("address", H85), "#" & CELL("address", INDEX(_xlpm.TableValueColumn, _xlpm.TableRowNum)) ), _xlpm.LinkLabel, IF(ISNA(_xlpm.TableRowNum), NotFoundLabelCell, "in " & _xlpm.LookupTableName ), HYPERLINK(_xlpm.LinkTarget, _xlpm.LinkLabel) )} -> in AlternativeMimumumTaxThresholdsTable
B86: Marginal Rate: | C86: =_xlfn.XLOOKUP(TRUE, FederalIncomeTaxRateTable[IsSelected], FederalIncomeTaxRateTable[Federal Tax Rate], NotFoundLabelCell) -> 0.22 | D86: {=_xlfn.LET( _xlpm.LookupTableName, "FederalIncomeTaxRateTable", _xlpm.ValueColumnName, "Federal Tax Rate", _xlpm.TableValueColumn, INDIRECT(_xlpm.LookupTableName & "[" & _xlpm.ValueColumnName & "]"), _xlpm.TableRowNum, _xlfn.XMATCH(TRUE, INDIRECT(_xlpm.LookupTableName & "[IsSelected]")), _xlpm.LinkTarget, IF(ISNA(_xlpm.TableRowNum), "#" & CELL("address", D86), "#" & CELL("address", INDEX(_xlpm.TableValueColumn, _xlpm.TableRowNum)) ), _xlpm.LinkLabel, IF(ISNA(_xlpm.TableRowNum), NotFoundLabelCell, "in " & _xlpm.LookupTableName ), HYPERLINK(_xlpm.LinkTarget, _xlpm.LinkLabel) )} -> in FederalIncomeTaxRateTable | F86: Phaseout Threshold: | G86: =_xlfn.XLOOKUP(TRUE, AlternativeMimumumTaxThresholdsTable[IsSelected], AlternativeMimumumTaxThresholdsTable[Phaseout Threshold], NotFoundLabelCell) -> 626350 | H86: {=_xlfn.LET( _xlpm.LookupTableName, "AlternativeMimumumTaxThresholdsTable", _xlpm.ValueColumnName, "Phaseout Threshold", _xlpm.TableValueColumn, INDIRECT(_xlpm.LookupTableName & "[" & _xlpm.ValueColumnName & "]"), _xlpm.TableRowNum, _xlfn.XMATCH(TRUE, INDIRECT(_xlpm.LookupTableName & "[IsSelected]")), _xlpm.LinkTarget, IF(ISNA(_xlpm.TableRowNum), "#" & CELL("address", H86), "#" & CELL("address", INDEX(_xlpm.TableValueColumn, _xlpm.TableRowNum)) ), _xlpm.LinkLabel, IF(ISNA(_xlpm.TableRowNum), NotFoundLabelCell, "in " & _xlpm.LookupTableName ), HYPERLINK(_xlpm.LinkTarget, _xlpm.LinkLabel) )} -> in AlternativeMimumumTaxThresholdsTable
B87: Marginal rate Bracket Start: | C87: =_xlfn.XLOOKUP(TRUE, FederalIncomeTaxRateTable[IsSelected], FederalIncomeTaxRateTable[RangeStart], NotFoundLabelCell) -> 48475 | D87: {=_xlfn.LET( _xlpm.LookupTableName, "FederalIncomeTaxRateTable", _xlpm.ValueColumnName, "RangeStart", _xlpm.TableValueColumn, INDIRECT(_xlpm.LookupTableName & "[" & _xlpm.ValueColumnName & "]"), _xlpm.TableRowNum, _xlfn.XMATCH(TRUE, INDIRECT(_xlpm.LookupTableName & "[IsSelected]")), _xlpm.LinkTarget, IF(ISNA(_xlpm.TableRowNum), "#" & CELL("address", D87), "#" & CELL("address", INDEX(_xlpm.TableValueColumn, _xlpm.TableRowNum)) ), _xlpm.LinkLabel, IF(ISNA(_xlpm.TableRowNum), NotFoundLabelCell, "in " & _xlpm.LookupTableName ), HYPERLINK(_xlpm.LinkTarget, _xlpm.LinkLabel) )} -> in FederalIncomeTaxRateTable | F87: AMTI above Phaseout Threshold: | G87: =MAX( G83 - G86, 0) -> 0
F88: Exemption Reduction due to Phaseout: | G88: =G87 * 0.25 -> 0
B89: Subtotal of lower rate brackets: | C89: =IF( C84 = 0, 0, _xlfn.XLOOKUP(TRUE, FederalIncomeTaxRateTable[IsSelected], FederalIncomeTaxRateTable[SumLowerRanges], NotFoundLabelCell) ) -> 5578.5 | D89: {=_xlfn.LET( _xlpm.LookupTableName, "FederalIncomeTaxRateTable", _xlpm.ValueColumnName, "SumLowerRanges", _xlpm.TableValueColumn, INDIRECT(_xlpm.LookupTableName & "[" & _xlpm.ValueColumnName & "]"), _xlpm.TableRowNum, _xlfn.XMATCH(TRUE, INDIRECT(_xlpm.LookupTableName & "[IsSelected]")), _xlpm.LinkTarget, IF(ISNA(_xlpm.TableRowNum), "#" & CELL("address", D89), "#" & CELL("address", INDEX(_xlpm.TableValueColumn, _xlpm.TableRowNum)) ), _xlpm.LinkLabel, IF(ISNA(_xlpm.TableRowNum), NotFoundLabelCell, "in " & _xlpm.LookupTableName ), HYPERLINK(_xlpm.LinkTarget, _xlpm.LinkLabel) )} -> in FederalIncomeTaxRateTable | F89: Actually Applicable AMT Excemption: | G89: =MAX( G85 - G88, 0 ) -> 88100
B90: Subtotal in marginal rate bracket: | C90: =IF( C84 = 0, 0, (C84 - C87) * C86 ) -> 5175.5
F91: Actual AMT-Taxable Amount: | G91: =MAX(G83-G89, 0) -> 0
B92: Total Regular Income Tax: | C92: =C89 + C90 -> 10754 | D92: =_xlfn.LET( _xlpm.FormulaText, _xlfn.FORMULATEXT(C92), _xlpm.FormulaText ) -> =C89 + C90
F93: Marginal Rate: | G93: =_xlfn.XLOOKUP(TRUE, AlternativeMinimumTaxRateTable[IsSelected], AlternativeMinimumTaxRateTable[AMT Rate], NotFoundLabelCell) -> 0.26 | H93: {=_xlfn.LET( _xlpm.LookupTableName, "AlternativeMinimumTaxRateTable", _xlpm.ValueColumnName, "AMT Rate", _xlpm.TableValueColumn, INDIRECT(_xlpm.LookupTableName & "[" & _xlpm.ValueColumnName & "]"), _xlpm.TableRowNum, _xlfn.XMATCH(TRUE, INDIRECT(_xlpm.LookupTableName & "[IsSelected]")), _xlpm.LinkTarget, IF(ISNA(_xlpm.TableRowNum), "#" & CELL("address", H93), "#" & CELL("address", INDEX(_xlpm.TableValueColumn, _xlpm.TableRowNum)) ), _xlpm.LinkLabel, IF(ISNA(_xlpm.TableRowNum), NotFoundLabelCell, "in " & _xlpm.LookupTableName ), HYPERLINK(_xlpm.LinkTarget, _xlpm.LinkLabel) )} -> in AlternativeMinimumTaxRateTable
B94: as % of applicable gross income: | C94: =C92 / C78 -> 0.1168913 | D94: =_xlfn.LET( _xlpm.FormulaText, _xlfn.FORMULATEXT(C94), _xlpm.FormulaText ) -> = C92 / C78 | F94: Marginal rate Bracket Start: | G94: =_xlfn.XLOOKUP(TRUE, AlternativeMinimumTaxRateTable[IsSelected], AlternativeMinimumTaxRateTable[RangeStart], NotFoundLabelCell) -> 0 | H94: {=_xlfn.LET( _xlpm.LookupTableName, "AlternativeMinimumTaxRateTable", _xlpm.ValueColumnName, "RangeStart", _xlpm.TableValueColumn, INDIRECT(_xlpm.LookupTableName & "[" & _xlpm.ValueColumnName & "]"), _xlpm.TableRowNum, _xlfn.XMATCH(TRUE, INDIRECT(_xlpm.LookupTableName & "[IsSelected]")), _xlpm.LinkTarget, IF(ISNA(_xlpm.TableRowNum), "#" & CELL("address", H94), "#" & CELL("address", INDEX(_xlpm.TableValueColumn, _xlpm.TableRowNum)) ), _xlpm.LinkLabel, IF(ISNA(_xlpm.TableRowNum), NotFoundLabelCell, "in " & _xlpm.LookupTableName ), HYPERLINK(_xlpm.LinkTarget, _xlpm.LinkLabel) )} -> in AlternativeMinimumTaxRateTable
B95: as % of applicable taxable income: | C95: =C92 / C84 -> 0.14936111 | D95: =_xlfn.LET( _xlpm.FormulaText, _xlfn.FORMULATEXT(C95), _xlpm.FormulaText ) -> = C92 / C84
F96: Subtotal of lower rate brackets: | G96: =IF( G91 = 0, 0, _xlfn.XLOOKUP(TRUE, AlternativeMinimumTaxRateTable[IsSelected], AlternativeMinimumTaxRateTable[SumLowerRanges], NotFoundLabelCell) ) -> 0 | H96: {=_xlfn.LET( _xlpm.LookupTableName, "AlternativeMinimumTaxRateTable", _xlpm.ValueColumnName, "SumLowerRanges", _xlpm.TableValueColumn, INDIRECT(_xlpm.LookupTableName & "[" & _xlpm.ValueColumnName & "]"), _xlpm.TableRowNum, _xlfn.XMATCH(TRUE, INDIRECT(_xlpm.LookupTableName & "[IsSelected]")), _xlpm.LinkTarget, IF(ISNA(_xlpm.TableRowNum), "#" & CELL("address", H96), "#" & CELL("address", INDEX(_xlpm.TableValueColumn, _xlpm.TableRowNum)) ), _xlpm.LinkLabel, IF(ISNA(_xlpm.TableRowNum), NotFoundLabelCell, "in " & _xlpm.LookupTableName ), HYPERLINK(_xlpm.LinkTarget, _xlpm.LinkLabel) )} -> in AlternativeMinimumTaxRateTable
F97: Subtotal in marginal rate bracket: | G97: =IF( G91 = 0, 0, (G91 - G94) * G93 ) -> 0
F99: Total Alternamive Minumum Tax: | G99: =G96 + G97 -> 0 | H99: =_xlfn.LET( _xlpm.FormulaText, _xlfn.FORMULATEXT(G99), _xlpm.FormulaText ) -> =G96 + G97
F101: as % of applicable gross income: | G101: =G99 / G78 -> 0 | H101: =_xlfn.LET( _xlpm.FormulaText, _xlfn.FORMULATEXT(G101), _xlpm.FormulaText ) -> = G99 / G78
F102: as % of applicable taxable income: | G102: =G99 / G83 -> 0 | H102: =_xlfn.LET( _xlpm.FormulaText, _xlfn.FORMULATEXT(G102), _xlpm.FormulaText ) -> = G99 / G83
B103: Long Term Capital Gain Tax (LTCG)
B105: =$F$25 -> Total Long-term Capital Gains: | C105: =G25 -> 5000 | D105: =_xlfn.LET( _xlpm.FormulaText, _xlfn.FORMULATEXT(C105), HYPERLINK( "#" & SUBSTITUTE(_xlpm.FormulaText, "=", ""), _xlpm.FormulaText ) ) -> = G25
B107: LTCG bracket range Start: | C107: =C84 -> 72000 | D107: =_xlfn.LET( _xlpm.FormulaText, _xlfn.FORMULATEXT(C107), HYPERLINK( "#" & SUBSTITUTE(_xlpm.FormulaText, "=", ""), _xlpm.FormulaText ) ) -> = C84
B108: Marginal rate: | C108: =_xlfn.XLOOKUP(TRUE, LongTermCapitalGainsTaxRateTable[IsBracketStart], LongTermCapitalGainsTaxRateTable[LTCG Rate], NotFoundLabelCell) -> 0.15 | D108: {=_xlfn.LET( _xlpm.LookupTableName, "LongTermCapitalGainsTaxRateTable", _xlpm.ValueColumnName, "LTCG Rate", _xlpm.TableValueColumn, INDIRECT(_xlpm.LookupTableName & "[" & _xlpm.ValueColumnName & "]"), _xlpm.TableRowNum, _xlfn.XMATCH(TRUE, INDIRECT(_xlpm.LookupTableName & "[IsBracketStart]")), _xlpm.LinkTarget, IF(ISNA(_xlpm.TableRowNum), "#" & CELL("address", D108), "#" & CELL("address", INDEX(_xlpm.TableValueColumn, _xlpm.TableRowNum)) ), _xlpm.LinkLabel, IF(ISNA(_xlpm.TableRowNum), NotFoundLabelCell, "in " & _xlpm.LookupTableName ), HYPERLINK(_xlpm.LinkTarget, _xlpm.LinkLabel) )} -> in LongTermCapitalGainsTaxRateTable
B109: Marginal rate bracket start: | C109: =_xlfn.XLOOKUP(TRUE, LongTermCapitalGainsTaxRateTable[IsBracketStart], LongTermCapitalGainsTaxRateTable[RangeStart], NotFoundLabelCell) -> 48350 | D109: {=_xlfn.LET( _xlpm.LookupTableName, "LongTermCapitalGainsTaxRateTable", _xlpm.ValueColumnName, "RangeStart", _xlpm.TableValueColumn, INDIRECT(_xlpm.LookupTableName & "[" & _xlpm.ValueColumnName & "]"), _xlpm.TableRowNum, _xlfn.XMATCH(TRUE, INDIRECT(_xlpm.LookupTableName & "[IsBracketStart]")), _xlpm.LinkTarget, IF(ISNA(_xlpm.TableRowNum), "#" & CELL("address", D109), "#" & CELL("address", INDEX(_xlpm.TableValueColumn, _xlpm.TableRowNum)) ), _xlpm.LinkLabel, IF(ISNA(_xlpm.TableRowNum), NotFoundLabelCell, "in " & _xlpm.LookupTableName ), HYPERLINK(_xlpm.LinkTarget, _xlpm.LinkLabel) )} -> in LongTermCapitalGainsTaxRateTable
B110: Subtotal of lower rate brackets: | C110: =IF( C107 = 0, 0, _xlfn.XLOOKUP(TRUE, LongTermCapitalGainsTaxRateTable[IsBracketStart], LongTermCapitalGainsTaxRateTable[SumLowerRanges], NotFoundLabelCell) ) -> 0 | D110: {=_xlfn.LET( _xlpm.LookupTableName, "LongTermCapitalGainsTaxRateTable", _xlpm.ValueColumnName, "SumLowerRanges", _xlpm.TableValueColumn, INDIRECT(_xlpm.LookupTableName & "[" & _xlpm.ValueColumnName & "]"), _xlpm.TableRowNum, _xlfn.XMATCH(TRUE, INDIRECT(_xlpm.LookupTableName & "[IsBracketStart]")), _xlpm.LinkTarget, IF(ISNA(_xlpm.TableRowNum), "#" & CELL("address", D110), "#" & CELL("address", INDEX(_xlpm.TableValueColumn, _xlpm.TableRowNum)) ), _xlpm.LinkLabel, IF(ISNA(_xlpm.TableRowNum), NotFoundLabelCell, "in " & _xlpm.LookupTableName ), HYPERLINK(_xlpm.LinkTarget, _xlpm.LinkLabel) )} -> in LongTermCapitalGainsTaxRateTable
B111: Subtotal in marginal rate bracket: | C111: =IF( C107 = 0, 0, (C107 - C109) * C108 ) -> 3547.5
B112: LTCG bracket range Start Tax: | C112: =C110 + C111 -> 3547.5 | D112: =_xlfn.LET( _xlpm.FormulaText, _xlfn.FORMULATEXT(C112), _xlpm.FormulaText ) -> = C110 + C111
B114: LTCG T bracket range End: | C114: =C107 + C105 -> 77000 | D114: =_xlfn.LET( _xlpm.FormulaText, _xlfn.FORMULATEXT(C114), _xlpm.FormulaText ) -> = C107 + C105
B115: Marginal rate: | C115: =_xlfn.XLOOKUP(TRUE, LongTermCapitalGainsTaxRateTable[IsBracketEnd], LongTermCapitalGainsTaxRateTable[LTCG Rate], NotFoundLabelCell) -> 0.15 | D115: {=_xlfn.LET( _xlpm.LookupTableName, "LongTermCapitalGainsTaxRateTable", _xlpm.ValueColumnName, "LTCG Rate", _xlpm.TableValueColumn, INDIRECT(_xlpm.LookupTableName & "[" & _xlpm.ValueColumnName & "]"), _xlpm.TableRowNum, _xlfn.XMATCH(TRUE, INDIRECT(_xlpm.LookupTableName & "[IsBracketEnd]")), _xlpm.LinkTarget, IF(ISNA(_xlpm.TableRowNum), "#" & CELL("address", D115), "#" & CELL("address", INDEX(_xlpm.TableValueColumn, _xlpm.TableRowNum)) ), _xlpm.LinkLabel, IF(ISNA(_xlpm.TableRowNum), NotFoundLabelCell, "in " & _xlpm.LookupTableName ), HYPERLINK(_xlpm.LinkTarget, _xlpm.LinkLabel) )} -> in LongTermCapitalGainsTaxRateTable
B116: Marginal rate bracket start: | C116: =_xlfn.XLOOKUP(TRUE, LongTermCapitalGainsTaxRateTable[IsBracketEnd], LongTermCapitalGainsTaxRateTable[RangeStart], NotFoundLabelCell) -> 48350 | D116: {=_xlfn.LET( _xlpm.LookupTableName, "LongTermCapitalGainsTaxRateTable", _xlpm.ValueColumnName, "RangeStart", _xlpm.TableValueColumn, INDIRECT(_xlpm.LookupTableName & "[" & _xlpm.ValueColumnName & "]"), _xlpm.TableRowNum, _xlfn.XMATCH(TRUE, INDIRECT(_xlpm.LookupTableName & "[IsBracketEnd]")), _xlpm.LinkTarget, IF(ISNA(_xlpm.TableRowNum), "#" & CELL("address", D116), "#" & CELL("address", INDEX(_xlpm.TableValueColumn, _xlpm.TableRowNum)) ), _xlpm.LinkLabel, IF(ISNA(_xlpm.TableRowNum), NotFoundLabelCell, "in " & _xlpm.LookupTableName ), HYPERLINK(_xlpm.LinkTarget, _xlpm.LinkLabel) )} -> in LongTermCapitalGainsTaxRateTable
B117: Subtotal of lower rate brackets: | C117: =IF( C114 = 0, 0, _xlfn.XLOOKUP(TRUE, LongTermCapitalGainsTaxRateTable[IsBracketEnd], LongTermCapitalGainsTaxRateTable[SumLowerRanges], NotFoundLabelCell) ) -> 0 | D117: {=_xlfn.LET( _xlpm.LookupTableName, "LongTermCapitalGainsTaxRateTable", _xlpm.ValueColumnName, "SumLowerRanges", _xlpm.TableValueColumn, INDIRECT(_xlpm.LookupTableName & "[" & _xlpm.ValueColumnName & "]"), _xlpm.TableRowNum, _xlfn.XMATCH(TRUE, INDIRECT(_xlpm.LookupTableName & "[IsBracketEnd]")), _xlpm.LinkTarget, IF(ISNA(_xlpm.TableRowNum), "#" & CELL("address", D117), "#" & CELL("address", INDEX(_xlpm.TableValueColumn, _xlpm.TableRowNum)) ), _xlpm.LinkLabel, IF(ISNA(_xlpm.TableRowNum), NotFoundLabelCell, "in " & _xlpm.LookupTableName ), HYPERLINK(_xlpm.LinkTarget, _xlpm.LinkLabel) )} -> in LongTermCapitalGainsTaxRateTable
B118: Subtotal in marginal rate bracket: | C118: =IF( C114 = 0, 0, (C114 - C116) * C115 ) -> 4297.5
B119: LTCG bracket range End Tax: | C119: =C117 + C118 -> 4297.5 | D119: =_xlfn.LET( _xlpm.FormulaText, _xlfn.FORMULATEXT(C119), _xlpm.FormulaText ) -> = C117 + C118
B121: Total Long Term Capital Gains Tax: | C121: =C119 - C112 -> 750 | D121: =_xlfn.LET( _xlpm.FormulaText, _xlfn.FORMULATEXT(C121), _xlpm.FormulaText ) -> = C119 - C112
B123: as % of long-term capital gains: | C123: =C121 / C105 -> 0.15 | D123: =_xlfn.LET( _xlpm.FormulaText, _xlfn.FORMULATEXT(C123), _xlpm.FormulaText ) -> = C121 / C105

Sheet Parameters
B2: This tab contains the tax computation parameters for different Tax Years, Income Brackets, and Filing Satuses.
B3: The `IsSelected` columns are auto-populated based on the inputs on the `Estimator` tab.
B6: =_xlfn.LET( _xlpm.HandleFormulaText, _xlfn.FORMULATEXT(D6), MID(_xlpm.HandleFormulaText, 2, FIND("[", _xlpm.HandleFormulaText) - 2) ) -> FilingStatusTable | C6: Handle: | D6: =FilingStatusTable[[#Headers],[Filing Status]] -> Filing Status | F6: In Range Label: | G6: ✔
C7: =_xlfn.LET( _xlpm.CountSelected, COUNTIF(FilingStatusTable[IsSelected], TRUE), IF( _xlpm.CountSelected = 1, SelectionValidLabelCell, "Error: " & _xlpm.CountSelected & " rows selected") ) -> Valid | F7: Out Of Range Label: | G7: OutOfRange
B8: Filing Status | C8: IsSelected | F8: Not Found Label: | G8: Not Found
B9: Single | C9: =(FilingStatusTable[[#This Row],[Filing Status]] = EstimateInputFilingStatusCell) -> TRUE | F9: Selection Valid Label: | G9: Valid
B10: Married Filing Jointly | C10: =(FilingStatusTable[[#This Row],[Filing Status]] = EstimateInputFilingStatusCell) -> FALSE | F10: Max Income: | G10: 10000000
B11: Married Filing Separately | C11: =(FilingStatusTable[[#This Row],[Filing Status]] = EstimateInputFilingStatusCell) -> FALSE
B12: Head of Household | C12: =(FilingStatusTable[[#This Row],[Filing Status]] = EstimateInputFilingStatusCell) -> FALSE
F14: =_xlfn.LET( _xlpm.HandleFormulaText, _xlfn.FORMULATEXT(H14), MID(_xlpm.HandleFormulaText, 2, FIND("[", _xlpm.HandleFormulaText) - 2) ) -> MedicareWageTaxRateTable | G14: Handle: | H14: =MedicareWageTaxRateTable[[#Headers],[Medicare Rate]] -> Medicare Rate
L15: =_xlfn.LET( _xlpm.CountSelected, COUNTIF(MedicareWageTaxRateTable[IsSelected], TRUE), IF( _xlpm.CountSelected = 1, SelectionValidLabelCell, "Error: " & _xlpm.CountSelected & " rows selected") ) -> Valid
B16: =_xlfn.LET( _xlpm.HandleFormulaText, _xlfn.FORMULATEXT(D16), MID(_xlpm.HandleFormulaText, 2, FIND("[", _xlpm.HandleFormulaText) - 2) ) -> SupportedYearsTable | C16: Handle: | D16: =SupportedYearsTable[[#Headers],[Tax Year]] -> Tax Year | F16: Filing Status | G16: Tax Year | H16: Medicare Rate | I16: RangeStart | J16: RangeEnd | K16: SumLowerRanges | L16: IsSelected
C17: =_xlfn.LET( _xlpm.CountSelected, COUNTIF(SupportedYearsTable[IsSelected], TRUE), IF( _xlpm.CountSelected = 1, SelectionValidLabelCell, "Error: " & _xlpm.CountSelected & " rows selected") ) -> Valid | F17: Single | G17: 2024 | H17: 0.0145 | I17: 0 | J17: 200000 | K17: 0 | L17: =AND( (MedicareWageTaxRateTable[[#This Row],[Tax Year]] = EstimateInputTaxYearCell), (MedicareWageTaxRateTable[[#This Row],[Filing Status]] = EstimateInputFilingStatusCell), (MedicareWageTaxRateTable[[#This Row],[RangeStart]] < Estimator!$C$59), (MedicareWageTaxRateTable[[#This Row],[RangeEnd]] >= Estimator!$C$59) ) -> FALSE
B18: Tax Year | C18: IsSelected | F18: Single | G18: 2024 | H18: =$H17 + 0.009 -> 0.0235 | I18: =$J17 -> 200000 | J18: =MaxIncomeCell -> 10000000 | K18: =$J17*$H17 -> 2900 | L18: =AND( (MedicareWageTaxRateTable[[#This Row],[Tax Year]] = EstimateInputTaxYearCell), (MedicareWageTaxRateTable[[#This Row],[Filing Status]] = EstimateInputFilingStatusCell), (MedicareWageTaxRateTable[[#This Row],[RangeStart]] < Estimator!$C$59), (MedicareWageTaxRateTable[[#This Row],[RangeEnd]] >= Estimator!$C$59) ) -> FALSE
B19: 2024 | C19: =(SupportedYearsTable[[#This Row],[Tax Year]] = EstimateInputTaxYearCell) -> FALSE | F19: Married Filing Jointly | G19: 2024 | H19: 0.0145 | I19: 0 | J19: 250000 | K19: 0 | L19: =AND( (MedicareWageTaxRateTable[[#This Row],[Tax Year]] = EstimateInputTaxYearCell), (MedicareWageTaxRateTable[[#This Row],[Filing Status]] = EstimateInputFilingStatusCell), (MedicareWageTaxRateTable[[#This Row],[RangeStart]] < Estimator!$C$59), (MedicareWageTaxRateTable[[#This Row],[RangeEnd]] >= Estimator!$C$59) ) -> FALSE
B20: 2025 | C20: =(SupportedYearsTable[[#This Row],[Tax Year]] = EstimateInputTaxYearCell) -> TRUE | F20: Married Filing Jointly | G20: 2024 | H20: =$H19 + 0.009 -> 0.0235 | I20: =$J19 -> 250000 | J20: =MaxIncomeCell -> 10000000 | K20: =$J19*$H19 -> 3625 | L20: =AND( (MedicareWageTaxRateTable[[#This Row],[Tax Year]] = EstimateInputTaxYearCell), (MedicareWageTaxRateTable[[#This Row],[Filing Status]] = EstimateInputFilingStatusCell), (MedicareWageTaxRateTable[[#This Row],[RangeStart]] < Estimator!$C$59), (MedicareWageTaxRateTable[[#This Row],[RangeEnd]] >= Estimator!$C$59) ) -> FALSE
F21: Married Filing Separately | G21: 2024 | H21: 0.0145 | I21: 0 | J21: 125000 | K21: 0 | L21: =AND( (MedicareWageTaxRateTable[[#This Row],[Tax Year]] = EstimateInputTaxYearCell), (MedicareWageTaxRateTable[[#This Row],[Filing Status]] = EstimateInputFilingStatusCell), (MedicareWageTaxRateTable[[#This Row],[RangeStart]] < Estimator!$C$59), (MedicareWageTaxRateTable[[#This Row],[RangeEnd]] >= Estimator!$C$59) ) -> FALSE
F22: Married Filing Separately | G22: 2024 | H22: =$H21 + 0.009 -> 0.0235 | I22: =$J21 -> 125000 | J22: =MaxIncomeCell -> 10000000 | K22: =$J21*$H21 -> 1812.5 | L22: =AND( (MedicareWageTaxRateTable[[#This Row],[Tax Year]] = EstimateInputTaxYearCell), (MedicareWageTaxRateTable[[#This Row],[Filing Status]] = EstimateInputFilingStatusCell), (MedicareWageTaxRateTable[[#This Row],[RangeStart]] < Estimator!$C$59), (MedicareWageTaxRateTable[[#This Row],[RangeEnd]] >= Estimator!$C$59) ) -> FALSE
F23: Head of Household | G23: 2024 | H23: 0.0145 | I23: 0 | J23: 200000 | K23: 0 | L23: =AND( (MedicareWageTaxRateTable[[#This Row],[Tax Year]] = EstimateInputTaxYearCell), (MedicareWageTaxRateTable[[#This Row],[Filing Status]] = EstimateInputFilingStatusCell), (MedicareWageTaxRateTable[[#This Row],[RangeStart]] < Estimator!$C$59), (MedicareWageTaxRateTable[[#This Row],[RangeEnd]] >= Estimator!$C$59) ) -> FALSE
F24: Head of Household | G24: 2024 | H24: =$H23 + 0.009 -> 0.0235 | I24: =$J23 -> 200000 | J24: =MaxIncomeCell -> 10000000 | K24: =$J23*$H23 -> 2900 | L24: =AND( (MedicareWageTaxRateTable[[#This Row],[Tax Year]] = EstimateInputTaxYearCell), (MedicareWageTaxRateTable[[#This Row],[Filing Status]] = EstimateInputFilingStatusCell), (MedicareWageTaxRateTable[[#This Row],[RangeStart]] < Estimator!$C$59), (MedicareWageTaxRateTable[[#This Row],[RangeEnd]] >= Estimator!$C$59) ) -> FALSE
L25: =AND( (MedicareWageTaxRateTable[[#This Row],[Tax Year]] = EstimateInputTaxYearCell), (MedicareWageTaxRateTable[[#This Row],[Filing Status]] = EstimateInputFilingStatusCell), (MedicareWageTaxRateTable[[#This Row],[RangeStart]] < Estimator!$C$59), (MedicareWageTaxRateTable[[#This Row],[RangeEnd]] >= Estimator!$C$59) ) -> FALSE
F26: Single | G26: 2025 | H26: 0.0145 | I26: 0 | J26: 200000 | K26: 0 | L26: =AND( (MedicareWageTaxRateTable[[#This Row],[Tax Year]] = EstimateInputTaxYearCell), (MedicareWageTaxRateTable[[#This Row],[Filing Status]] = EstimateInputFilingStatusCell), (MedicareWageTaxRateTable[[#This Row],[RangeStart]] < Estimator!$C$59), (MedicareWageTaxRateTable[[#This Row],[RangeEnd]] >= Estimator!$C$59) ) -> TRUE
F27: Single | G27: 2025 | H27: =$H26 + 0.009 -> 0.0235 | I27: =$J26 -> 200000 | J27: =MaxIncomeCell -> 10000000 | K27: =$J26*$H26 -> 2900 | L27: =AND( (MedicareWageTaxRateTable[[#This Row],[Tax Year]] = EstimateInputTaxYearCell), (MedicareWageTaxRateTable[[#This Row],[Filing Status]] = EstimateInputFilingStatusCell), (MedicareWageTaxRateTable[[#This Row],[RangeStart]] < Estimator!$C$59), (MedicareWageTaxRateTable[[#This Row],[RangeEnd]] >= Estimator!$C$59) ) -> FALSE
F28: Married Filing Jointly | G28: 2025 | H28: 0.0145 | I28: 0 | J28: 250000 | K28: 0 | L28: =AND( (MedicareWageTaxRateTable[[#This Row],[Tax Year]] = EstimateInputTaxYearCell), (MedicareWageTaxRateTable[[#This Row],[Filing Status]] = EstimateInputFilingStatusCell), (MedicareWageTaxRateTable[[#This Row],[RangeStart]] < Estimator!$C$59), (MedicareWageTaxRateTable[[#This Row],[RangeEnd]] >= Estimator!$C$59) ) -> FALSE
F29: Married Filing Jointly | G29: 2025 | H29: =$H28 + 0.009 -> 0.0235 | I29: =$J28 -> 250000 | J29: =MaxIncomeCell -> 10000000 | K29: =$J28*$H28 -> 3625 | L29: =AND( (MedicareWageTaxRateTable[[#This Row],[Tax Year]] = EstimateInputTaxYearCell), (MedicareWageTaxRateTable[[#This Row],[Filing Status]] = EstimateInputFilingStatusCell), (MedicareWageTaxRateTable[[#This Row],[RangeStart]] < Estimator!$C$59), (MedicareWageTaxRateTable[[#This Row],[RangeEnd]] >= Estimator!$C$59) ) -> FALSE
F30: Married Filing Separately | G30: 2025 | H30: 0.0145 | I30: 0 | J30: 125000 | K30: 0 | L30: =AND( (MedicareWageTaxRateTable[[#This Row],[Tax Year]] = EstimateInputTaxYearCell), (MedicareWageTaxRateTable[[#This Row],[Filing Status]] = EstimateInputFilingStatusCell), (MedicareWageTaxRateTable[[#This Row],[RangeStart]] < Estimator!$C$59), (MedicareWageTaxRateTable[[#This Row],[RangeEnd]] >= Estimator!$C$59) ) -> FALSE
F31: Married Filing Separately | G31: 2025 | H31: =$H30 + 0.009 -> 0.0235 | I31: =$J30 -> 125000 | J31: =MaxIncomeCell -> 10000000 | K31: =$J30*$H30 -> 1812.5 | L31: =AND( (MedicareWageTaxRateTable[[#This Row],[Tax Year]] = EstimateInputTaxYearCell), (MedicareWageTaxRateTable[[#This Row],[Filing Status]] = EstimateInputFilingStatusCell), (MedicareWageTaxRateTable[[#This Row],[RangeStart]] < Estimator!$C$59), (MedicareWageTaxRateTable[[#This Row],[RangeEnd]] >= Estimator!$C$59) ) -> FALSE
F32: Head of Household | G32: 2025 | H32: 0.0145 | I32: 0 | J32: 200000 | K32: 0 | L32: =AND( (MedicareWageTaxRateTable[[#This Row],[Tax Year]] = EstimateInputTaxYearCell), (MedicareWageTaxRateTable[[#This Row],[Filing Status]] = EstimateInputFilingStatusCell), (MedicareWageTaxRateTable[[#This Row],[RangeStart]] < Estimator!$C$59), (MedicareWageTaxRateTable[[#This Row],[RangeEnd]] >= Estimator!$C$59) ) -> FALSE
F33: Head of Household | G33: 2025 | H33: =$H32 + 0.009 -> 0.0235 | I33: =$J32 -> 200000 | J33: =MaxIncomeCell -> 10000000 | K33: =$J32*$H32 -> 2900 | L33: =AND( (MedicareWageTaxRateTable[[#This Row],[Tax Year]] = EstimateInputTaxYearCell), (MedicareWageTaxRateTable[[#This Row],[Filing Status]] = EstimateInputFilingStatusCell), (MedicareWageTaxRateTable[[#This Row],[RangeStart]] < Estimator!$C$59), (MedicareWageTaxRateTable[[#This Row],[RangeEnd]] >= Estimator!$C$59) ) -> FALSE
F37: =_xlfn.LET( _xlpm.HandleFormulaText, _xlfn.FORMULATEXT(H37), MID(_xlpm.HandleFormulaText, 2, FIND("[", _xlpm.HandleFormulaText) - 2) ) -> MedicareNetInvestIncomeTaxTable | G37: Handle: | H37: =MedicareNetInvestIncomeTaxTable[[#Headers],[NetInvestInc Rate]] -> NetInvestInc Rate
J38: =_xlfn.LET( _xlpm.CountSelected, COUNTIF(MedicareNetInvestIncomeTaxTable[IsSelected], TRUE), IF( _xlpm.CountSelected = 1, SelectionValidLabelCell, "Error: " & _xlpm.CountSelected & " rows selected") ) -> Valid
F39: Status LabelId | G39: Tax Year | H39: NetInvestInc Rate | I39: Modified AGI Threshold | J39: IsSelected
F40: Single | G40: 2024 | H40: 0.038 | I40: 200000 | J40: =AND( (MedicareNetInvestIncomeTaxTable[[#This Row],[Tax Year]] = EstimateInputTaxYearCell), (MedicareNetInvestIncomeTaxTable[[#This Row],[Status LabelId]] = EstimateInputFilingStatusCell) ) -> FALSE
F41: Married Filing Jointly | G41: 2024 | H41: 0.038 | I41: 250000 | J41: =AND( (MedicareNetInvestIncomeTaxTable[[#This Row],[Tax Year]] = EstimateInputTaxYearCell), (MedicareNetInvestIncomeTaxTable[[#This Row],[Status LabelId]] = EstimateInputFilingStatusCell) ) -> FALSE
F42: Married Filing Separately | G42: 2024 | H42: 0.038 | I42: 125000 | J42: =AND( (MedicareNetInvestIncomeTaxTable[[#This Row],[Tax Year]] = EstimateInputTaxYearCell), (MedicareNetInvestIncomeTaxTable[[#This Row],[Status LabelId]] = EstimateInputFilingStatusCell) ) -> FALSE
F43: Head of Household | G43: 2024 | H43: 0.038 | I43: 200000 | J43: =AND( (MedicareNetInvestIncomeTaxTable[[#This Row],[Tax Year]] = EstimateInputTaxYearCell), (MedicareNetInvestIncomeTaxTable[[#This Row],[Status LabelId]] = EstimateInputFilingStatusCell) ) -> FALSE
J44: =AND( (MedicareNetInvestIncomeTaxTable[[#This Row],[Tax Year]] = EstimateInputTaxYearCell), (MedicareNetInvestIncomeTaxTable[[#This Row],[Status LabelId]] = EstimateInputFilingStatusCell) ) -> FALSE
F45: Single | G45: 2025 | H45: 0.038 | I45: 200000 | J45: =AND( (MedicareNetInvestIncomeTaxTable[[#This Row],[Tax Year]] = EstimateInputTaxYearCell), (MedicareNetInvestIncomeTaxTable[[#This Row],[Status LabelId]] = EstimateInputFilingStatusCell) ) -> TRUE
F46: Married Filing Jointly | G46: 2025 | H46: 0.038 | I46: 250000 | J46: =AND( (MedicareNetInvestIncomeTaxTable[[#This Row],[Tax Year]] = EstimateInputTaxYearCell), (MedicareNetInvestIncomeTaxTable[[#This Row],[Status LabelId]] = EstimateInputFilingStatusCell) ) -> FALSE
F47: Married Filing Separately | G47: 2025 | H47: 0.038 | I47: 125000 | J47: =AND( (MedicareNetInvestIncomeTaxTable[[#This Row],[Tax Year]] = EstimateInputTaxYearCell), (MedicareNetInvestIncomeTaxTable[[#This Row],[Status LabelId]] = EstimateInputFilingStatusCell) ) -> FALSE
F48: Head of Household | G48: 2025 | H48: 0.038 | I48: 200000 | J48: =AND( (MedicareNetInvestIncomeTaxTable[[#This Row],[Tax Year]] = EstimateInputTaxYearCell), (MedicareNetInvestIncomeTaxTable[[#This Row],[Status LabelId]] = EstimateInputFilingStatusCell) ) -> FALSE
F52: =_xlfn.LET( _xlpm.HandleFormulaText, _xlfn.FORMULATEXT(H52), MID(_xlpm.HandleFormulaText, 2, FIND("[", _xlpm.HandleFormulaText) - 2) ) -> SocialSecurityTaxRateTable | G52: Handle: | H52: =SocialSecurityTaxRateTable[[#Headers],[SocialSecurity Rate]] -> SocialSecurity Rate
K53: =_xlfn.LET( _xlpm.CountSelected, COUNTIF(SocialSecurityTaxRateTable[IsSelected], TRUE), IF( _xlpm.CountSelected = 1, SelectionValidLabelCell, "Error: " & _xlpm.CountSelected & " rows selected") ) -> Valid
F54: Status LabelId | G54: Tax Year | H54: SocialSecurity Rate | I54: Max Taxable Income | J54: SumLowerRanges | K54: IsSelected
F55: Single | G55: 2024 | H55: 0.062 | I55: 168600 | J55: 0 | K55: =AND( (SocialSecurityTaxRateTable[[#This Row],[Tax Year]] = EstimateInputTaxYearCell), (SocialSecurityTaxRateTable[[#This Row],[Status LabelId]] = EstimateInputFilingStatusCell) ) -> FALSE
F56: Married Filing Jointly | G56: 2024 | H56: 0.062 | I56: 168600 | J56: 0 | K56: =AND( (SocialSecurityTaxRateTable[[#This Row],[Tax Year]] = EstimateInputTaxYearCell), (SocialSecurityTaxRateTable[[#This Row],[Status LabelId]] = EstimateInputFilingStatusCell) ) -> FALSE
F57: Married Filing Separately | G57: 2024 | H57: 0.062 | I57: 168600 | J57: 0 | K57: =AND( (SocialSecurityTaxRateTable[[#This Row],[Tax Year]] = EstimateInputTaxYearCell), (SocialSecurityTaxRateTable[[#This Row],[Status LabelId]] = EstimateInputFilingStatusCell) ) -> FALSE
F58: Head of Household | G58: 2024 | H58: 0.062 | I58: 168600 | J58: 0 | K58: =AND( (SocialSecurityTaxRateTable[[#This Row],[Tax Year]] = EstimateInputTaxYearCell), (SocialSecurityTaxRateTable[[#This Row],[Status LabelId]] = EstimateInputFilingStatusCell) ) -> FALSE
K59: =AND( (SocialSecurityTaxRateTable[[#This Row],[Tax Year]] = EstimateInputTaxYearCell), (SocialSecurityTaxRateTable[[#This Row],[Status LabelId]] = EstimateInputFilingStatusCell) ) -> FALSE
F60: Single | G60: 2025 | H60: 0.062 | I60: 176100 | J60: 0 | K60: =AND( (SocialSecurityTaxRateTable[[#This Row],[Tax Year]] = EstimateInputTaxYearCell), (SocialSecurityTaxRateTable[[#This Row],[Status LabelId]] = EstimateInputFilingStatusCell) ) -> TRUE
F61: Married Filing Jointly | G61: 2025 | H61: 0.062 | I61: 176100 | J61: 0 | K61: =AND( (SocialSecurityTaxRateTable[[#This Row],[Tax Year]] = EstimateInputTaxYearCell), (SocialSecurityTaxRateTable[[#This Row],[Status LabelId]] = EstimateInputFilingStatusCell) ) -> FALSE
F62: Married Filing Separately | G62: 2025 | H62: 0.062 | I62: 176100 | J62: 0 | K62: =AND( (SocialSecurityTaxRateTable[[#This Row],[Tax Year]] = EstimateInputTaxYearCell), (SocialSecurityTaxRateTable[[#This Row],[Status LabelId]] = EstimateInputFilingStatusCell) ) -> FALSE
F63: Head of Household | G63: 2025 | H63: 0.062 | I63: 176100 | J63: 0 | K63: =AND( (SocialSecurityTaxRateTable[[#This Row],[Tax Year]] = EstimateInputTaxYearCell), (SocialSecurityTaxRateTable[[#This Row],[Status LabelId]] = EstimateInputFilingStatusCell) ) -> FALSE
F67: =_xlfn.LET( _xlpm.HandleFormulaText, _xlfn.FORMULATEXT(H67), MID(_xlpm.HandleFormulaText, 2, FIND("[", _xlpm.HandleFormulaText) - 2) ) -> StandardDeductionAmountTable | G67: Handle: | H67: =StandardDeductionAmountTable[[#Headers],[Standard Deduction Amount]] -> Standard Deduction Amount
I68: =_xlfn.LET( _xlpm.CountSelected, COUNTIF(StandardDeductionAmountTable[IsSelected], TRUE), IF( _xlpm.CountSelected = 1, SelectionValidLabelCell, "Error: " & _xlpm.CountSelected & " rows selected") ) -> Valid
F69: Status LabelId | G69: Tax Year | H69: Standard Deduction Amount | I69: IsSelected
F70: Single | G70: 2024 | H70: 14600 | I70: =AND( (StandardDeductionAmountTable[[#This Row],[Tax Year]] = EstimateInputTaxYearCell), (StandardDeductionAmountTable[[#This Row],[Status LabelId]] = EstimateInputFilingStatusCell) ) -> FALSE
F71: Married Filing Jointly | G71: 2024 | H71: 29200 | I71: =AND( (StandardDeductionAmountTable[[#This Row],[Tax Year]] = EstimateInputTaxYearCell), (StandardDeductionAmountTable[[#This Row],[Status LabelId]] = EstimateInputFilingStatusCell) ) -> FALSE
F72: Married Filing Separately | G72: 2024 | H72: 14600 | I72: =AND( (StandardDeductionAmountTable[[#This Row],[Tax Year]] = EstimateInputTaxYearCell), (StandardDeductionAmountTable[[#This Row],[Status LabelId]] = EstimateInputFilingStatusCell) ) -> FALSE
F73: Head of Household | G73: 2024 | H73: 21900 | I73: =AND( (StandardDeductionAmountTable[[#This Row],[Tax Year]] = EstimateInputTaxYearCell), (StandardDeductionAmountTable[[#This Row],[Status LabelId]] = EstimateInputFilingStatusCell) ) -> FALSE
I74: =AND( (StandardDeductionAmountTable[[#This Row],[Tax Year]] = EstimateInputTaxYearCell), (StandardDeductionAmountTable[[#This Row],[Status LabelId]] = EstimateInputFilingStatusCell) ) -> FALSE
F75: Single | G75: 2025 | H75: 15000 | I75: =AND( (StandardDeductionAmountTable[[#This Row],[Tax Year]] = EstimateInputTaxYearCell), (StandardDeductionAmountTable[[#This Row],[Status LabelId]] = EstimateInputFilingStatusCell) ) -> TRUE
F76: Married Filing Jointly | G76: 2025 | H76: 30000 | I76: =AND( (StandardDeductionAmountTable[[#This Row],[Tax Year]] = EstimateInputTaxYearCell), (StandardDeductionAmountTable[[#This Row],[Status LabelId]] = EstimateInputFilingStatusCell) ) -> FALSE
F77: Married Filing Separately | G77: 2025 | H77: 15000 | I77: =AND( (StandardDeductionAmountTable[[#This Row],[Tax Year]] = EstimateInputTaxYearCell), (StandardDeductionAmountTable[[#This Row],[Status LabelId]] = EstimateInputFilingStatusCell) ) -> FALSE
F78: Head of Household | G78: 2025 | H78: 22500 | I78: =AND( (StandardDeductionAmountTable[[#This Row],[Tax Year]] = EstimateInputTaxYearCell), (StandardDeductionAmountTable[[#This Row],[Status LabelId]] = EstimateInputFilingStatusCell) ) -> FALSE
F82: =_xlfn.LET( _xlpm.HandleFormulaText, _xlfn.FORMULATEXT(H82), MID(_xlpm.HandleFormulaText, 2, FIND("[", _xlpm.HandleFormulaText) - 2) ) -> FederalIncomeTaxRateTable | G82: Handle: | H82: =FederalIncomeTaxRateTable[[#Headers],[Federal Tax Rate]] -> Federal Tax Rate
L83: =_xlfn.LET( _xlpm.CountSelected, COUNTIF(FederalIncomeTaxRateTable[IsSelected], TRUE), IF( _xlpm.CountSelected = 1, SelectionValidLabelCell, "Error: " & _xlpm.CountSelected & " rows selected") ) -> Valid
F84: Status LabelId | G84: Tax Year | H84: Federal Tax Rate | I84: RangeStart | J84: RangeEnd | K84: SumLowerRanges | L84: IsSelected
F85: Single | G85: 2024 | H85: 0.1 | I85: 0 | J85: 11600 | K85: 0 | L85: =AND( (FederalIncomeTaxRateTable[[#This Row],[Tax Year]] = EstimateInputTaxYearCell), (FederalIncomeTaxRateTable[[#This Row],[Status LabelId]] = EstimateInputFilingStatusCell), (FederalIncomeTaxRateTable[[#This Row],[RangeStart]] < Estimator!$C$84), (FederalIncomeTaxRateTable[[#This Row],[RangeEnd]] >= Estimator!$C$84) ) -> FALSE
F86: Single | G86: 2024 | H86: 0.12 | I86: =$J85 -> 11600 | J86: 47150 | K86: =$K85 + ($J85 - $I85) * $H85 -> 1160 | L86: =AND( (FederalIncomeTaxRateTable[[#This Row],[Tax Year]] = EstimateInputTaxYearCell), (FederalIncomeTaxRateTable[[#This Row],[Status LabelId]] = EstimateInputFilingStatusCell), (FederalIncomeTaxRateTable[[#This Row],[RangeStart]] < Estimator!$C$84), (FederalIncomeTaxRateTable[[#This Row],[RangeEnd]] >= Estimator!$C$84) ) -> FALSE
F87: Single | G87: 2024 | H87: 0.22 | I87: =$J86 -> 47150 | J87: 100525 | K87: =$K86 + ($J86 - $I86) * $H86 -> 5426 | L87: =AND( (FederalIncomeTaxRateTable[[#This Row],[Tax Year]] = EstimateInputTaxYearCell), (FederalIncomeTaxRateTable[[#This Row],[Status LabelId]] = EstimateInputFilingStatusCell), (FederalIncomeTaxRateTable[[#This Row],[RangeStart]] < Estimator!$C$84), (FederalIncomeTaxRateTable[[#This Row],[RangeEnd]] >= Estimator!$C$84) ) -> FALSE
F88: Single | G88: 2024 | H88: 0.24 | I88: =$J87 -> 100525 | J88: 191950 | K88: =$K87 + ($J87 - $I87) * $H87 -> 17168.5 | L88: =AND( (FederalIncomeTaxRateTable[[#This Row],[Tax Year]] = EstimateInputTaxYearCell), (FederalIncomeTaxRateTable[[#This Row],[Status LabelId]] = EstimateInputFilingStatusCell), (FederalIncomeTaxRateTable[[#This Row],[RangeStart]] < Estimator!$C$84), (FederalIncomeTaxRateTable[[#This Row],[RangeEnd]] >= Estimator!$C$84) ) -> FALSE
F89: Single | G89: 2024 | H89: 0.32 | I89: =$J88 -> 191950 | J89: 243725 | K89: =$K88 + ($J88 - $I88) * $H88 -> 39110.5 | L89: =AND( (FederalIncomeTaxRateTable[[#This Row],[Tax Year]] = EstimateInputTaxYearCell), (FederalIncomeTaxRateTable[[#This Row],[Status LabelId]] = EstimateInputFilingStatusCell), (FederalIncomeTaxRateTable[[#This Row],[RangeStart]] < Estimator!$C$84), (FederalIncomeTaxRateTable[[#This Row],[RangeEnd]] >= Estimator!$C$84) ) -> FALSE
F90: Single | G90: 2024 | H90: 0.35 | I90: =$J89 -> 243725 | J90: 609350 | K90: =$K89 + ($J89 - $I89) * $H89 -> 55678.5 | L90: =AND( (FederalIncomeTaxRateTable[[#This Row],[Tax Year]] = EstimateInputTaxYearCell), (FederalIncomeTaxRateTable[[#This Row],[Status LabelId]] = EstimateInputFilingStatusCell), (FederalIncomeTaxRateTable[[#This Row],[RangeStart]] < Estimator!$C$84), (FederalIncomeTaxRateTable[[#This Row],[RangeEnd]] >= Estimator!$C$84) ) -> FALSE
F91: Single | G91: 2024 | H91: 0.37 | I91: =$J90 -> 609350 | J91: =MaxIncomeCell -> 10000000 | K91: =$K90 + ($J90 - $I90) * $H90 -> 183647.25 | L91: =AND( (FederalIncomeTaxRateTable[[#This Row],[Tax Year]] = EstimateInputTaxYearCell), (FederalIncomeTaxRateTable[[#This Row],[Status LabelId]] = EstimateInputFilingStatusCell), (FederalIncomeTaxRateTable[[#This Row],[RangeStart]] < Estimator!$C$84), (FederalIncomeTaxRateTable[[#This Row],[RangeEnd]] >= Estimator!$C$84) ) -> FALSE
F92: Married Filing Jointly | G92: 2024 | H92: 0.1 | I92: 0 | J92: 23200 | K92: 0 | L92: =AND( (FederalIncomeTaxRateTable[[#This Row],[Tax Year]] = EstimateInputTaxYearCell), (FederalIncomeTaxRateTable[[#This Row],[Status LabelId]] = EstimateInputFilingStatusCell), (FederalIncomeTaxRateTable[[#This Row],[RangeStart]] < Estimator!$C$84), (FederalIncomeTaxRateTable[[#This Row],[RangeEnd]] >= Estimator!$C$84) ) -> FALSE
F93: Married Filing Jointly | G93: 2024 | H93: 0.12 | I93: =$J92 -> 23200 | J93: 94300 | K93: =$K92 + ($J92 - $I92) * $H92 -> 2320 | L93: =AND( (FederalIncomeTaxRateTable[[#This Row],[Tax Year]] = EstimateInputTaxYearCell), (FederalIncomeTaxRateTable[[#This Row],[Status LabelId]] = EstimateInputFilingStatusCell), (FederalIncomeTaxRateTable[[#This Row],[RangeStart]] < Estimator!$C$84), (FederalIncomeTaxRateTable[[#This Row],[RangeEnd]] >= Estimator!$C$84) ) -> FALSE
F94: Married Filing Jointly | G94: 2024 | H94: 0.22 | I94: =$J93 -> 94300 | J94: 201050 | K94: =$K93 + ($J93 - $I93) * $H93 -> 10852 | L94: =AND( (FederalIncomeTaxRateTable[[#This Row],[Tax Year]] = EstimateInputTaxYearCell), (FederalIncomeTaxRateTable[[#This Row],[Status LabelId]] = EstimateInputFilingStatusCell), (FederalIncomeTaxRateTable[[#This Row],[RangeStart]] < Estimator!$C$84), (FederalIncomeTaxRateTable[[#This Row],[RangeEnd]] >= Estimator!$C$84) ) -> FALSE
F95: Married Filing Jointly | G95: 2024 | H95: 0.24 | I95: =$J94 -> 201050 | J95: 383900 | K95: =$K94 + ($J94 - $I94) * $H94 -> 34337 | L95: =AND( (FederalIncomeTaxRateTable[[#This Row],[Tax Year]] = EstimateInputTaxYearCell), (FederalIncomeTaxRateTable[[#This Row],[Status LabelId]] = EstimateInputFilingStatusCell), (FederalIncomeTaxRateTable[[#This Row],[RangeStart]] < Estimator!$C$84), (FederalIncomeTaxRateTable[[#This Row],[RangeEnd]] >= Estimator!$C$84) ) -> FALSE
F96: Married Filing Jointly | G96: 2024 | H96: 0.32 | I96: =$J95 -> 383900 | J96: 487450 | K96: =$K95 + ($J95 - $I95) * $H95 -> 78221 | L96: =AND( (FederalIncomeTaxRateTable[[#This Row],[Tax Year]] = EstimateInputTaxYearCell), (FederalIncomeTaxRateTable[[#This Row],[Status LabelId]] = EstimateInputFilingStatusCell), (FederalIncomeTaxRateTable[[#This Row],[RangeStart]] < Estimator!$C$84), (FederalIncomeTaxRateTable[[#This Row],[RangeEnd]] >= Estimator!$C$84) ) -> FALSE
F97: Married Filing Jointly | G97: 2024 | H97: 0.35 | I97: =$J96 -> 487450 | J97: 731200 | K97: =$K96 + ($J96 - $I96) * $H96 -> 111357 | L97: =AND( (FederalIncomeTaxRateTable[[#This Row],[Tax Year]] = EstimateInputTaxYearCell), (FederalIncomeTaxRateTable[[#This Row],[Status LabelId]] = EstimateInputFilingStatusCell), (FederalIncomeTaxRateTable[[#This Row],[RangeStart]] < Estimator!$C$84), (FederalIncomeTaxRateTable[[#This Row],[RangeEnd]] >= Estimator!$C$84) ) -> FALSE
F98: Married Filing Jointly | G98: 2024 | H98: 0.37 | I98: =$J97 -> 731200 | J98: =MaxIncomeCell -> 10000000 | K98: =$K97 + ($J97 - $I97) * $H97 -> 196669.5 | L98: =AND( (FederalIncomeTaxRateTable[[#This Row],[Tax Year]] = EstimateInputTaxYearCell), (FederalIncomeTaxRateTable[[#This Row],[Status LabelId]] = EstimateInputFilingStatusCell), (FederalIncomeTaxRateTable[[#This Row],[RangeStart]] < Estimator!$C$84), (FederalIncomeTaxRateTable[[#This Row],[RangeEnd]] >= Estimator!$C$84) ) -> FALSE
F99: Married Filing Separately | G99: 2024 | H99: 0.1 | I99: 0 | J99: 11600 | K99: 0 | L99: =AND( (FederalIncomeTaxRateTable[[#This Row],[Tax Year]] = EstimateInputTaxYearCell), (FederalIncomeTaxRateTable[[#This Row],[Status LabelId]] = EstimateInputFilingStatusCell), (FederalIncomeTaxRateTable[[#This Row],[RangeStart]] < Estimator!$C$84), (FederalIncomeTaxRateTable[[#This Row],[RangeEnd]] >= Estimator!$C$84) ) -> FALSE
F100: Married Filing Separately | G100: 2024 | H100: 0.12 | I100: =$J99 -> 11600 | J100: 47150 | K100: =$K99 + ($J99 - $I99) * $H99 -> 1160 | L100: =AND( (FederalIncomeTaxRateTable[[#This Row],[Tax Year]] = EstimateInputTaxYearCell), (FederalIncomeTaxRateTable[[#This Row],[Status LabelId]] = EstimateInputFilingStatusCell), (FederalIncomeTaxRateTable[[#This Row],[RangeStart]] < Estimator!$C$84), (FederalIncomeTaxRateTable[[#This Row],[RangeEnd]] >= Estimator!$C$84) ) -> FALSE
F101: Married Filing Separately | G101: 2024 | H101: 0.22 | I101: =$J100 -> 47150 | J101: 100525 | K101: =$K100 + ($J100 - $I100) * $H100 -> 5426 | L101: =AND( (FederalIncomeTaxRateTable[[#This Row],[Tax Year]] = EstimateInputTaxYearCell), (FederalIncomeTaxRateTable[[#This Row],[Status LabelId]] = EstimateInputFilingStatusCell), (FederalIncomeTaxRateTable[[#This Row],[RangeStart]] < Estimator!$C$84), (FederalIncomeTaxRateTable[[#This Row],[RangeEnd]] >= Estimator!$C$84) ) -> FALSE
F102: Married Filing Separately | G102: 2024 | H102: 0.24 | I102: =$J101 -> 100525 | J102: 191950 | K102: =$K101 + ($J101 - $I101) * $H101 -> 17168.5 | L102: =AND( (FederalIncomeTaxRateTable[[#This Row],[Tax Year]] = EstimateInputTaxYearCell), (FederalIncomeTaxRateTable[[#This Row],[Status LabelId]] = EstimateInputFilingStatusCell), (FederalIncomeTaxRateTable[[#This Row],[RangeStart]] < Estimator!$C$84), (FederalIncomeTaxRateTable[[#This Row],[RangeEnd]] >= Estimator!$C$84) ) -> FALSE
F103: Married Filing Separately | G103: 2024 | H103: 0.32 | I103: =$J102 -> 191950 | J103: 243725 | K103: =$K102 + ($J102 - $I102) * $H102 -> 39110.5 | L103: =AND( (FederalIncomeTaxRateTable[[#This Row],[Tax Year]] = EstimateInputTaxYearCell), (FederalIncomeTaxRateTable[[#This Row],[Status LabelId]] = EstimateInputFilingStatusCell), (FederalIncomeTaxRateTable[[#This Row],[RangeStart]] < Estimator!$C$84), (FederalIncomeTaxRateTable[[#This Row],[RangeEnd]] >= Estimator!$C$84) ) -> FALSE
F104: Married Filing Separately | G104: 2024 | H104: 0.35 | I104: =$J103 -> 243725 | J104: 365600 | K104: =$K103 + ($J103 - $I103) * $H103 -> 55678.5 | L104: =AND( (FederalIncomeTaxRateTable[[#This Row],[Tax Year]] = EstimateInputTaxYearCell), (FederalIncomeTaxRateTable[[#This Row],[Status LabelId]] = EstimateInputFilingStatusCell), (FederalIncomeTaxRateTable[[#This Row],[RangeStart]] < Estimator!$C$84), (FederalIncomeTaxRateTable[[#This Row],[RangeEnd]] >= Estimator!$C$84) ) -> FALSE
F105: Married Filing Separately | G105: 2024 | H105: 0.37 | I105: =$J104 -> 365600 | J105: =MaxIncomeCell -> 10000000 | K105: =$K104 + ($J104 - $I104) * $H104 -> 98334.75 | L105: =AND( (FederalIncomeTaxRateTable[[#This Row],[Tax Year]] = EstimateInputTaxYearCell), (FederalIncomeTaxRateTable[[#This Row],[Status LabelId]] = EstimateInputFilingStatusCell), (FederalIncomeTaxRateTable[[#This Row],[RangeStart]] < Estimator!$C$84), (FederalIncomeTaxRateTable[[#This Row],[RangeEnd]] >= Estimator!$C$84) ) -> FALSE
F106: Head of Household | G106: 2024 | H106: 0.1 | I106: 0 | J106: 16550 | K106: 0 | L106: =AND( (FederalIncomeTaxRateTable[[#This Row],[Tax Year]] = EstimateInputTaxYearCell), (FederalIncomeTaxRateTable[[#This Row],[Status LabelId]] = EstimateInputFilingStatusCell), (FederalIncomeTaxRateTable[[#This Row],[RangeStart]] < Estimator!$C$84), (FederalIncomeTaxRateTable[[#This Row],[RangeEnd]] >= Estimator!$C$84) ) -> FALSE
F107: Head of Household | G107: 2024 | H107: 0.12 | I107: =$J106 -> 16550 | J107: 63100 | K107: =$K106 + ($J106 - $I106) * $H106 -> 1655 | L107: =AND( (FederalIncomeTaxRateTable[[#This Row],[Tax Year]] = EstimateInputTaxYearCell), (FederalIncomeTaxRateTable[[#This Row],[Status LabelId]] = EstimateInputFilingStatusCell), (FederalIncomeTaxRateTable[[#This Row],[RangeStart]] < Estimator!$C$84), (FederalIncomeTaxRateTable[[#This Row],[RangeEnd]] >= Estimator!$C$84) ) -> FALSE
F108: Head of Household | G108: 2024 | H108: 0.22 | I108: =$J107 -> 63100 | J108: 100500 | K108: =$K107 + ($J107 - $I107) * $H107 -> 7241 | L108: =AND( (FederalIncomeTaxRateTable[[#This Row],[Tax Year]] = EstimateInputTaxYearCell), (FederalIncomeTaxRateTable[[#This Row],[Status LabelId]] = EstimateInputFilingStatusCell), (FederalIncomeTaxRateTable[[#This Row],[RangeStart]] < Estimator!$C$84), (FederalIncomeTaxRateTable[[#This Row],[RangeEnd]] >= Estimator!$C$84) ) -> FALSE
F109: Head of Household | G109: 2024 | H109: 0.24 | I109: =$J108 -> 100500 | J109: 191950 | K109: =$K108 + ($J108 - $I108) * $H108 -> 15469 | L109: =AND( (FederalIncomeTaxRateTable[[#This Row],[Tax Year]] = EstimateInputTaxYearCell), (FederalIncomeTaxRateTable[[#This Row],[Status LabelId]] = EstimateInputFilingStatusCell), (FederalIncomeTaxRateTable[[#This Row],[RangeStart]] < Estimator!$C$84), (FederalIncomeTaxRateTable[[#This Row],[RangeEnd]] >= Estimator!$C$84) ) -> FALSE
F110: Head of Household | G110: 2024 | H110: 0.32 | I110: =$J109 -> 191950 | J110: 243700 | K110: =$K109 + ($J109 - $I109) * $H109 -> 37417 | L110: =AND( (FederalIncomeTaxRateTable[[#This Row],[Tax Year]] = EstimateInputTaxYearCell), (FederalIncomeTaxRateTable[[#This Row],[Status LabelId]] = EstimateInputFilingStatusCell), (FederalIncomeTaxRateTable[[#This Row],[RangeStart]] < Estimator!$C$84), (FederalIncomeTaxRateTable[[#This Row],[RangeEnd]] >= Estimator!$C$84) ) -> FALSE
F111: Head of Household | G111: 2024 | H111: 0.35 | I111: =$J110 -> 243700 | J111: 609350 | K111: =$K110 + ($J110 - $I110) * $H110 -> 53977 | L111: =AND( (FederalIncomeTaxRateTable[[#This Row],[Tax Year]] = EstimateInputTaxYearCell), (FederalIncomeTaxRateTable[[#This Row],[Status LabelId]] = EstimateInputFilingStatusCell), (FederalIncomeTaxRateTable[[#This Row],[RangeStart]] < Estimator!$C$84), (FederalIncomeTaxRateTable[[#This Row],[RangeEnd]] >= Estimator!$C$84) ) -> FALSE
F112: Head of Household | G112: 2024 | H112: 0.37 | I112: =$J111 -> 609350 | J112: =MaxIncomeCell -> 10000000 | K112: =$K111 + ($J111 - $I111) * $H111 -> 181954.5 | L112: =AND( (FederalIncomeTaxRateTable[[#This Row],[Tax Year]] = EstimateInputTaxYearCell), (FederalIncomeTaxRateTable[[#This Row],[Status LabelId]] = EstimateInputFilingStatusCell), (FederalIncomeTaxRateTable[[#This Row],[RangeStart]] < Estimator!$C$84), (FederalIncomeTaxRateTable[[#This Row],[RangeEnd]] >= Estimator!$C$84) ) -> FALSE
L113: =AND( (FederalIncomeTaxRateTable[[#This Row],[Tax Year]] = EstimateInputTaxYearCell), (FederalIncomeTaxRateTable[[#This Row],[Status LabelId]] = EstimateInputFilingStatusCell), (FederalIncomeTaxRateTable[[#This Row],[RangeStart]] < Estimator!$C$84), (FederalIncomeTaxRateTable[[#This Row],[RangeEnd]] >= Estimator!$C$84) ) -> FALSE
F114: Single | G114: 2025 | H114: 0.1 | I114: 0 | J114: 11925 | K114: 0 | L114: =AND( (FederalIncomeTaxRateTable[[#This Row],[Tax Year]] = EstimateInputTaxYearCell), (FederalIncomeTaxRateTable[[#This Row],[Status LabelId]] = EstimateInputFilingStatusCell), (FederalIncomeTaxRateTable[[#This Row],[RangeStart]] < Estimator!$C$84), (FederalIncomeTaxRateTable[[#This Row],[RangeEnd]] >= Estimator!$C$84) ) -> FALSE
F115: Single | G115: 2025 | H115: 0.12 | I115: =$J114 -> 11925 | J115: 48475 | K115: =$K114 + ($J114 - $I114) * $H114 -> 1192.5 | L115: =AND( (FederalIncomeTaxRateTable[[#This Row],[Tax Year]] = EstimateInputTaxYearCell), (FederalIncomeTaxRateTable[[#This Row],[Status LabelId]] = EstimateInputFilingStatusCell), (FederalIncomeTaxRateTable[[#This Row],[RangeStart]] < Estimator!$C$84), (FederalIncomeTaxRateTable[[#This Row],[RangeEnd]] >= Estimator!$C$84) ) -> FALSE
F116: Single | G116: 2025 | H116: 0.22 | I116: =$J115 -> 48475 | J116: 103350 | K116: =$K115 + ($J115 - $I115) * $H115 -> 5578.5 | L116: =AND( (FederalIncomeTaxRateTable[[#This Row],[Tax Year]] = EstimateInputTaxYearCell), (FederalIncomeTaxRateTable[[#This Row],[Status LabelId]] = EstimateInputFilingStatusCell), (FederalIncomeTaxRateTable[[#This Row],[RangeStart]] < Estimator!$C$84), (FederalIncomeTaxRateTable[[#This Row],[RangeEnd]] >= Estimator!$C$84) ) -> TRUE
...
